Metadata-Version: 2.1
Name: a2y-hidcom
Version: 1.1.2
Summary: 此模块实现内核科技 USB（HID）转多通道UART 的驱动程序。
Home-page: http://www.sorobust.com/a2y/hidcom.html
Author: Yu Han
Author-email: hanjunyu@163.com
License: Private
Platform: Windows
Platform: Linux
Classifier: Development Status :: 4 - Beta
Classifier: Intended Audience :: Developers
Classifier: License :: Free For Educational Use
Classifier: Programming Language :: Python :: 3.5
Classifier: Operating System :: Microsoft :: Windows :: Windows 10
Classifier: Operating System :: POSIX :: Linux
License-File: LICENSE
Requires-Dist: pyusb >=1.2
Requires-Dist: libusb-package >=1.0.26.0
